LICENSE
README.md
setup.cfg
setup.py
jiosaavn/__init__.py
jiosaavn/jiosaavn.py
jiosaavn_python.egg-info/PKG-INFO
jiosaavn_python.egg-info/SOURCES.txt
jiosaavn_python.egg-info/dependency_links.txt
jiosaavn_python.egg-info/requires.txt
jiosaavn_python.egg-info/top_level.txt