Metadata-Version: 2.1
Name: jiosaavn-python
Version: 0.1
Summary: An unofficial Python3 wrapper for JioSaavn, a popular Indian music streaming service..
Home-page: https://github.com/abhichaudharii/jiosaavn-python
Download-URL: https://github.com/abhichaudharii/jiosaavn-python/archive/refs/tags/v0.1.tar.gz
Author: Abhishek Chaudhari
Author-email: abhichaudhari@protonmail.com
License: MIT
Keywords: JioSaavn,JioSaavn-API,Saavn,Saavn API,download songs,lyrics,playlist
Classifier: Development Status :: 3 - Alpha
Classifier: Intended Audience :: Developers
Classifier: Topic :: Software Development :: Build Tools
Classifier: License :: OSI Approved :: MIT License
Classifier: Programming Language :: Python :: 3.8
License-File: LICENSE
